{
  "@context": "https://openwashdata.org/",
  "@type": "Dataset",
  "name": "unhcrwash",
  "description": "This is a dataset on WASH indicators in refugee camps and settlements. The data was collected from the UNHCR Information Management System (IRIS) and was available on the UNHCR WASH dashboard. This dataset includes data from 227 sites and 36 countries. The source dashboard has since been retired, so this dataset is a fixed historical snapshot (2013 to 2024) that can no longer be regenerated.",
  "publisher": {
    "@type": "Organization",
    "name": "openwashdata @ Global Health Engineering, ETH Zurich",
    "url": "https://openwashdata.org/"
  },
  "datePublished": "2024-11-19",
  "license": "https://creativecommons.org/licenses/by/4.0/",
  "keywords": "refugee camps, unhcr, wash indicators, iris",
  "distribution": {
    "@type": "DataDownload",
    "url": "https://raw.githubusercontent.com/openwashdata/unhcrwash/main/inst/extdata/unhcrwash.csv",
    "contentUrl": "https://raw.githubusercontent.com/openwashdata/unhcrwash/main/inst/extdata/unhcrwash.csv",
    "encodingFormat": "text/csv"
  },
  "encodingFormat": "CSV",
  "version": "0.2.0",
  "spatialCoverage": {
    "@type": "Place",
    "name": "worldwide"
  },
  "temporalCoverage": {
    "@type": "DateTime",
    "startDate": "30.09.2013",
    "endDate": "31.12.2024"
  },
  "contactPoint": {
    "@type": "ContactPoint",
    "contactType": "Lars Schöbitz",
    "email": "lschoebitz@ethz.ch"
  }
}
